{
  "name": "Roger Moss",
  "age": 54,
  "address": {
    "street": "Pata Pike",
    "city": "Sibvotcaf",
    "state": "AZ",
    "zip": "76554"
  },
  "contact": {
    "phone": "(505) 584-8664",
    "servicePhone": "800232862"
  },
  "birthday": "1969-06-15T01:43:15.893Z",
  "ip": "88.52.1.224",
  "foo": "bar",
  "profile": {
    "about": "Ni ew fuptoivu espiksun satsefbo opaz silom epigij adu luhazjop vaod nol. De wo zemuh pit biupaha ne apocriw cu olu jalefur bodewulu somizki lapav bu gaeb nodazmu leb fuepi. Um saeg biw dopuv uta pegoc zomip wiwomuj fit jawi saoto tegu. To jecbigfa luaji baejrew ca li terho pufce tebiswi feb ponuteh miwarupe ifovew zohizdi ehvu notra jiunvom.",
    "bio": "Guko ejerevir irwapkon jiore rojha ij tahwu wefpuz hemcuwsuk tiadaca fesubo ak wewzetcaf uzuopo. Ifo bammuloh hajba dit tili bucun casan nabti jopsedna hagi gefrerob sasjaov duvzeb. Usutemew zoznos tev tethamgum lu nucrib cib bucocwo mijmanak rozu wodgetico uhnudsum. Evi zit ap atedinpiv zipo rujzag bur ke gewtiod leg re uneaf aje vagjailu serac ewdu."
  },
  "apiKey": "b23674faa32b721073690ec8cf54fbc737833749360cb15e2b3fa0db08589e56",
  "currency": {
    "code": "ILS",
    "name": "Israel Shekel"
  }
}