{
  "name": "Luis Logan",
  "age": 38,
  "address": {
    "street": "Kafac Manor",
    "city": "Egtebzem",
    "state": "NH",
    "zip": "13185"
  },
  "contact": {
    "phone": "(201) 778-9596",
    "servicePhone": "800728499"
  },
  "birthday": "1970-01-22T16:52:18.112Z",
  "ip": "240.226.119.18",
  "foo": "bar",
  "profile": {
    "about": "Juplarfac oceicinu lowoc tawujbaz cawoj mejgeme jaotjon pi fujjoje cemogica ga jijkih hatwa gidwij ni sot ec alihuwa. Lodobuj gihu iszaub ripe butcid fus atoadet gupha eklu cu diwdir onzar puteke. Vofpikgoj omsa mefepi uddod tuh ulmueho soja luf casoucu fonrinov lap jalutte nolabzod. Hirju wines ba caelfap mu fe zo pifunidu loflukhu gil bahahu rozhuw mowofivi new tem funzuzi cumim vakzi. Repek kuko oho picut wutakfip pu olaco vunme ijekot po reurti fec gow.",
    "bio": "Noro zavovi kedev puput fe gu iwki ja muto tifri ci ela. Jig so roil timcagor fiwbitem zosu so wej to gub pi ro fi. Pa olafu oskohel ri tiw pomowi vohamiw dediguzu iriimasiv ica kag lembuhu tanmot. Raakubu go komseete du nigoso tohmu tiize du cab ca hum pisocaguw aga."
  },
  "apiKey": "7e1fe470c8b6d8e56145e215438cb85717bec1018b7565666311e6b738c9f03b",
  "currency": {
    "code": "MUR",
    "name": "Mauritius Rupee"
  }
}