{
  "name": "Russell Cruz",
  "age": 41,
  "address": {
    "street": "Gargem Boulevard",
    "city": "Bovuvan",
    "state": "NC",
    "zip": "58975"
  },
  "contact": {
    "phone": "(263) 229-6952",
    "servicePhone": "800859677"
  },
  "birthday": "1993-08-01T06:15:26.243Z",
  "ip": "99.37.149.236",
  "foo": "bar",
  "profile": {
    "about": "Colwiza rubuef idnaz jugija wiazhi do mewobhim su hophun tocba ivuhi opo rohoz ofa huijoiz. To pe gi sarmasdel getlipgij cu suvjora zoke ogruiku gogcetawa aji imege ince. Bajbongi muh ca tegjuwje favop onaepo ket usiigipe at beirte ju cowpe eba. Komipa ca kihaslep jil igaj vuvo ve loim ap je norti nijhu. Bazu pufkolje gu je rihhibag elemoaju ju rijeipa ahu jimvir eb tubwu fa.",
    "bio": "Acake jezvi pi sowezca gej ri hocdupodo gesiviz godo webci piru hiz uw jum zubinew. Ku ejwisgi ka uvre aspade ac nalaga fibak moidopot ohkef nenenbaz abbe jum agisoom ot degtu uguvfov otoabawu. Bater ben got nik ji siasba dido rechuz jeguk enov ewso be voj ajesivo to fu. Obi koswib ujdo osekahapa uzbog muawwef piguh giwi nifuka jikikro gu ri icu. Hu on saobelu pus wusivez uztar wa janfiw nezvezu coj vuuvhov lacapwuz catabaj leheb callen jijiv kelesadas."
  },
  "apiKey": "57fe2e478bd881f01dc36394dc2d1dcae1fcf50b6bbb349f7316152bf0e2492c",
  "currency": {
    "code": "TVD",
    "name": "Tuvalu Dollar"
  }
}